pnumpy/__init__.py
pnumpy/pnCubeDecomp.py
pnumpy/pnDistArray.py
pnumpy/pnDomainPartitionIter.py
pnumpy/pnGhostedDistArray.py
pnumpy/pnLaplacian.py
pnumpy/pnMultiArrayIter.py
pnumpy/pnPartition.py
pnumpy/pnStencilOperator.py
pnumpy-1.4.2.dist-info/LICENSE
pnumpy-1.4.2.dist-info/METADATA
pnumpy-1.4.2.dist-info/WHEEL
pnumpy-1.4.2.dist-info/top_level.txt
pnumpy-1.4.2.dist-info/RECORD
