Metadata-Version: 2.1
Name: pnumpy
Version: 1.4.2
Summary: A very lightweight implementation of distributed arrays
Home-page: https://github.com/pletzer/pnumpy.git
Author: Alexander Pletzer
Author-email: alexander@gokliya.net
License: UNKNOWN
Platform: UNKNOWN
Requires-Dist: numpy
Requires-Dist: mpi4py
